odoo10_addon_analytic_partner_hr_timesheet_invoice-10.0.1.0.0-py2.7-nspkg.pth
odoo/addons/analytic_partner_hr_timesheet_invoice/README.rst
odoo/addons/analytic_partner_hr_timesheet_invoice/__init__.py
odoo/addons/analytic_partner_hr_timesheet_invoice/__manifest__.py
odoo/addons/analytic_partner_hr_timesheet_invoice/i18n/de.po
odoo/addons/analytic_partner_hr_timesheet_invoice/i18n/es.po
odoo/addons/analytic_partner_hr_timesheet_invoice/i18n/es_MX.po
odoo/addons/analytic_partner_hr_timesheet_invoice/i18n/fi.po
odoo/addons/analytic_partner_hr_timesheet_invoice/i18n/fr.po
odoo/addons/analytic_partner_hr_timesheet_invoice/i18n/pt.po
odoo/addons/analytic_partner_hr_timesheet_invoice/i18n/pt_BR.po
odoo/addons/analytic_partner_hr_timesheet_invoice/i18n/sl.po
odoo/addons/analytic_partner_hr_timesheet_invoice/models/__init__.py
odoo/addons/analytic_partner_hr_timesheet_invoice/models/sale_order_line.py
odoo/addons/analytic_partner_hr_timesheet_invoice/static/description/icon.png
odoo/addons/analytic_partner_hr_timesheet_invoice/static/description/icon.svg
odoo/addons/analytic_partner_hr_timesheet_invoice/tests/__init__.py
odoo/addons/analytic_partner_hr_timesheet_invoice/tests/test_analytic_partner_hr_timesheet_invoice.py
odoo10_addon_analytic_partner_hr_timesheet_invoice-10.0.1.0.0.dist-info/DESCRIPTION.rst
odoo10_addon_analytic_partner_hr_timesheet_invoice-10.0.1.0.0.dist-info/METADATA
odoo10_addon_analytic_partner_hr_timesheet_invoice-10.0.1.0.0.dist-info/RECORD
odoo10_addon_analytic_partner_hr_timesheet_invoice-10.0.1.0.0.dist-info/WHEEL
odoo10_addon_analytic_partner_hr_timesheet_invoice-10.0.1.0.0.dist-info/metadata.json
odoo10_addon_analytic_partner_hr_timesheet_invoice-10.0.1.0.0.dist-info/namespace_packages.txt
odoo10_addon_analytic_partner_hr_timesheet_invoice-10.0.1.0.0.dist-info/top_level.txt
